graphs_mcsteestu/__init__.py
graphs_mcsteestu/heapq.py
graphs_mcsteestu/sp.py
graphs_mcsteestu-0.0.2.dist-info/METADATA
graphs_mcsteestu-0.0.2.dist-info/WHEEL
graphs_mcsteestu-0.0.2.dist-info/RECORD
