Metadata-Version: 2.4
Name: graphs_mcsteestu
Version: 0.0.2
Summary: A package containing an implementation for a priority queue algorithm and dijkstra's algorithm.
Project-URL: Homepage, https://github.com/msteenstu/graph-package
Project-URL: Bug Tracker, https://github.com/msteenstu/graph-package/issues
Author-email: Mckenna Steenbock <msteenbock@student.cccs.edu>
Classifier: License :: OSI Approved :: MIT License
Classifier: Operating System :: OS Independent
Classifier: Programming Language :: Python :: 3
Requires-Python: >=3.7
